boatrace/__init__.py
boatrace/official/__init__.py
boatrace/official/exceptions.py
boatrace/official/factories.py
boatrace/official/v1707/__init__.py
boatrace/official/v1707/decorators.py
boatrace/official/v1707/factories.py
boatrace/official/v1707/utils.py
boatrace/official/v1707/pages/monthly_schedule_page/__init__.py
boatrace/official/v1707/pages/monthly_schedule_page/location.py
boatrace/official/v1707/pages/monthly_schedule_page/scraping.py
boatrace/official/v1707/pages/monthly_schedule_page/tests/test_location.py
boatrace/official/v1707/pages/monthly_schedule_page/tests/test_scraping.py
boatrace/official/v1707/pages/pre_inspection_information_page/__init__.py
boatrace/official/v1707/pages/pre_inspection_information_page/location.py
boatrace/official/v1707/pages/pre_inspection_information_page/scraping.py
boatrace/official/v1707/pages/pre_inspection_information_page/tests/__init__.py
boatrace/official/v1707/pages/pre_inspection_information_page/tests/test_location.py
boatrace/official/v1707/pages/pre_inspection_information_page/tests/test_scraping.py
boatrace/official/v1707/pages/race/__init__.py
boatrace/official/v1707/pages/race/common.py
boatrace/official/v1707/pages/race/utils.py
boatrace/official/v1707/pages/race/before_information_page/__init__.py
boatrace/official/v1707/pages/race/before_information_page/location.py
boatrace/official/v1707/pages/race/before_information_page/scraping.py
boatrace/official/v1707/pages/race/before_information_page/tests/__init__.py
boatrace/official/v1707/pages/race/before_information_page/tests/test_location.py
boatrace/official/v1707/pages/race/before_information_page/tests/test_scraping.py
boatrace/official/v1707/pages/race/entry_page/__init__.py
boatrace/official/v1707/pages/race/entry_page/location.py
boatrace/official/v1707/pages/race/entry_page/scraping.py
boatrace/official/v1707/pages/race/entry_page/tests/__init__.py
boatrace/official/v1707/pages/race/entry_page/tests/test_location.py
boatrace.official-0.0.7.dist-info/LICENSE.txt
boatrace.official-0.0.7.dist-info/METADATA
boatrace.official-0.0.7.dist-info/WHEEL
boatrace.official-0.0.7.dist-info/top_level.txt
boatrace.official-0.0.7.dist-info/RECORD
