Metadata-Version: 2.1
Name: boatrace.official
Version: 0.0.7
Summary: Utils for Japanese boatrace official web site
Author-email: k0kishima <okishimaxyz@gmail.com>
License: MIT License        
Keywords: boatrace,kyotei
Classifier: Programming Language :: Python :: 3.9
Classifier: Programming Language :: Python :: 3.10
Classifier: Programming Language :: Python :: 3.11
Requires-Python: >=3.9
License-File: LICENSE.txt
Requires-Dist: beautifulsoup4 (==4.11.1)
Requires-Dist: boatrace.models (==0.0.1)
Requires-Dist: numpy (==1.23.4)
